{
  "summary": {
    "position": "Postdoc",
    "institution": "King Fahd University of Petroleum and Minerals",
    "location": "Dhahran, Saudi Arabia",
    "department": "Information and Computer Science Department",
    "research_focus": [
      "Secure Software Development",
      "Software Security",
      "Artificial Intelligence in Software Engineering"
    ],
    "responsibilities": null,
    "employment_terms": {
      "duration": "2 years",
      "extension": "possibility of extension for an additional two years based on performance and mutual agreement"
    },
    "collaboration": null,
    "eligibility": {
      "qualifications": [
        "Ph.D. in Computer Science",
        "Ph.D. in Software Engineering",
        "Ph.D. in a closely related field",
        "Candidates currently holding postdoc positions are also encouraged to apply"
      ]
    },
    "submission_info": {
      "submission_link": null,
      "contact_person": {
        "name": "Prof. Mohammad Alshayeb",
        "email": "[log in to unmask]",
        "phone": "+(966) 13-860-4874"
      }
    },
    "website": "https://www.kfupm.edu.sa/",
    "event": null,
    "dates": null,
    "co_located_events": null,
    "registration": null,
    "description": "Seeking applications for two postdoc positions.",
    "submission_details": null,
    "publication_details": null,
    "important_dates": null,
    "program_highlights": null,
    "subject": null,
    "school": null,
    "closing_date": null,
    "candidate_requirements": null,
    "benefits": null,
    "equality_commitment": null,
    "visa_information": null,
    "topics_of_interest": [
      "Software Development",
      "Software Security",
      "Artificial Intelligence"
    ],
    "community_invitation": null,
    "academic_reputation": null,
    "affiliated_universities": null,
    "submission_guidelines": null,
    "timelines": null,
    "event_format": null,
    "program_committee": null,
    "publications_criteria": null,
    "conference_scope": null,
    "chairs": null,
    "call_for_contributions": null,
    "application_details": null,
    "applications_open_until": null,
    "registration_link": null
  }
}