{
  "has_body": true,
  "purpose": "LUT School of Engineering Sciences is announcing a job opening for a Professor in Artificial Intelligence for Software Engineering. The position is available at the Department of Software Engineering, which focuses on software development, digital transformation, and user-centered design. Candidates are expected to have research expertise in AI related to software engineering, with responsibilities including education, research, and administrative duties. The application process is open until 11 August 2025, and further details can be found in the provided links.",
  "cfp": {
    "cfp_candidate": false,
    "classify_cfp_purpose": null,
    "is_cfp_purpose": false
  },
  "is_cfp": null,
  "is_joint_call": {
    "is_joint_conf": false,
    "is_joint_work": false
  },
  "infos": {
    "infos": [],
    "conf_name_candidates": [],
    "conf_name_tokens": [],
    "conf_name_final": null,
    "work_name_candidates": [],
    "work_tokens": [],
    "start_date": null,
    "submission_deadline": null,
    "conference_website": null
  },
  "length": {
    "mail_text": 4147,
    "purpose": 569,
    "infos": 0
  }
}