{
  "has_body": true,
  "purpose": "The email is a call for Letters of Interest (LoI) to organize the European conference on Software Architecture (ECSA) for the years 2027 and onwards. It highlights the significance of ECSA as a premier conference in the field, inviting teams to express their intent to organize the event. The email outlines the requirements for the LoI, including details about the proposed General Chair, location, and supporting organizations. It also specifies the submission deadline and procedure for interested parties.",
  "cfp": {
    "cfp_candidate": false,
    "classify_cfp_purpose": null,
    "is_cfp_purpose": false
  },
  "is_cfp": null,
  "is_joint_call": {
    "is_joint_conf": false,
    "is_joint_work": false
  },
  "infos": {
    "infos": [],
    "conf_name_candidates": [],
    "conf_name_tokens": [],
    "conf_name_final": null,
    "work_name_candidates": [],
    "work_tokens": [],
    "start_date": null,
    "submission_deadline": null,
    "conference_website": null
  },
  "length": {
    "mail_text": 4308,
    "purpose": 509,
    "infos": 0
  }
}